plots/__init__.py
plots/blueprints/__init__.py
plots/blueprints/ehden_routes.py
plots/blueprints/htmlBuilderFunctions.py
plots/blueprints/pubmed_routes.py
plots/blueprints/user_routes.py
plots/blueprints/youtube_routes.py
plots/figures/__init__.py
plots/figures/ehden_course_completions.py
plots/figures/ehden_users.py
plots/figures/publications_citations.py
plots/figures/researchers.py
plots/figures/youtube_annual.py
plots/figures/youtube_monthly.py
plots/pages/ehden_course_completions.py
plots/pages/ehden_users.py
plots/pages/publications_citations.py
plots/pages/researchers.py
plots/pages/youtube_annual.py
plots/pages/youtube_monthly.py
plots/services/__init__.py
plots/services/db.py
plots/services/ehden_miner.py
plots/services/pubmed_miner.py
plots/services/pubmed_miner_test.py
plots/services/youtube_miner.py
plots/test/__init__.py
plots/test/course-stats.json
plots/test/ehden.json
plots/test/ehden_course_completions.json
plots/test/ehden_fixture.json
plots/test/ehden_users.json
plots/test/getPMArticles_searchAll.pkl
plots/test/mock_init_cosmos.py
plots/test/pub_med_cumulative_authors.json
plots/test/pub_med_fixture.json
plots/test/pub_med_new_authors.json
plots/test/pubmed.json
plots/test/pubmed_authors.json
plots/test/researchers.json
plots/test/schema.sql
plots/test/serpApi.pkl
plots/test/test.db
plots/test/you_tube_dashboard_fixture.json
plots/test/you_tube_fixture.json
plots/test/youtube.json
plots/test/youtube_monthly.json
community_dashboard_plots-0.0.2.dist-info/METADATA
community_dashboard_plots-0.0.2.dist-info/WHEEL
community_dashboard_plots-0.0.2.dist-info/top_level.txt
community_dashboard_plots-0.0.2.dist-info/RECORD
